MANIFEST.in
setup.py
sensproject/__init__.py
sensproject/projectcreator.py
sensproject.egg-info/PKG-INFO
sensproject.egg-info/SOURCES.txt
sensproject.egg-info/dependency_links.txt
sensproject.egg-info/entry_points.txt
sensproject.egg-info/top_level.txt
sensproject/skel/.ccsproject
sensproject/skel/.cproject
sensproject/skel/.project
sensproject/skel/Debug
sensproject/skel/leproject.cpp
sensproject/skel/main.cpp
sensproject/skel/targetConfigs
sensproject/skel/.settings/org.eclipse.cdt.codan.core.prefs
sensproject/skel/.settings/org.eclipse.cdt.debug.core.prefs
sensproject/skel/.settings/org.eclipse.core.resources.prefs
sensproject/skel/targetConfigs/MSP430F2617.ccxml
sensproject/skel/targetConfigs/readme.txt