Metadata-Version: 1.0
Name: sensproject
Version: 0.3.5
Summary: A simple script to create new Senscape project
Home-page: UNKNOWN
Author: Guillem Castro
Author-email: guillemcastro4@gmail.com
License: UNKNOWN
Platform: UNKNOWN
